<ConsultarNfseFaixa xmlns="http://tempuri.org/"><cabecalho><![CDATA[<CabecalhoEnvio Versao="0" xmlns="http://www.abrasf.org.br/ABRASF/arquivos/nfse.xsd"><CodigoIbge>%s</CodigoIbge><versaoDados>0</versaoDados><TpAmb>%s</TpAmb>%s</CabecalhoEnvio>]]></cabecalho><consultarNfseFaixaEnvio><![CDATA[<ConsultarNfseFaixaEnvio xmlns="http://www.abrasf.org.br/nfse.xsd">%s<Faixa><NumeroNfseInicial>%s</NumeroNfseInicial><NumeroNfseFinal>%s</NumeroNfseFinal></Faixa><Pagina>1</Pagina></ConsultarNfseFaixaEnvio>]]></consultarNfseFaixaEnvio></ConsultarNfseFaixa>